{
    "id": "70b78be7-2685-4983-bd7f-717f0b739103",
    "clientId": "survey-product-realm",
    "name": "survey-product Realm",
    "surrogateAuthRequired": false,
    "enabled": true,
    "clientAuthenticatorType": "client-secret",
    "redirectUris": [],
    "webOrigins": [],
    "notBefore": 0,
    "bearerOnly": true,
    "consentRequired": false,
    "standardFlowEnabled": true,
    "implicitFlowEnabled": false,
    "directAccessGrantsEnabled": false,
    "serviceAccountsEnabled": true,
    "publicClient": false,
    "frontchannelLogout": false,
    "protocol": "openid-connect",
    "attributes": {
        "saml.assertion.signature": "false",
        "saml.force.post.binding": "false",
        "saml.multivalued.roles": "false",
        "saml.encrypt": "false",
        "saml_force_name_id_format": "false",
        "saml.client.signature": "false",
        "saml.authnstatement": "false",
        "saml.server.signature": "false"
    },
    "fullScopeAllowed": true,
    "nodeReRegistrationTimeout": 0,
    "protocolMappers": [
        {
            "id": "16c8c40f-9eeb-4ed8-9d91-3fdf85907ea9",
            "name": "role list",
            "protocol": "saml",
            "protocolMapper": "saml-role-list-mapper",
            "consentRequired": false,
            "config": {
                "single": "false",
                "attribute.nameformat": "Basic",
                "attribute.name": "Role"
            }
        },
        {
            "id": "6e8ea7a1-9b3b-4358-876b-67c1c656ae98",
            "name": "given name",
            "protocol": "openid-connect",
            "protocolMapper": "oidc-usermodel-property-mapper",
            "consentRequired": true,
            "consentText": "${givenName}",
            "config": {
                "user.attribute": "firstName",
                "id.token.claim": "true",
                "access.token.claim": "true",
                "claim.name": "given_name",
                "jsonType.label": "String"
            }
        },
        {
            "id": "377336bb-0b74-4925-9779-c74b9b2bb741",
            "name": "email",
            "protocol": "openid-connect",
            "protocolMapper": "oidc-usermodel-property-mapper",
            "consentRequired": true,
            "consentText": "${email}",
            "config": {
                "user.attribute": "email",
                "id.token.claim": "true",
                "access.token.claim": "true",
                "claim.name": "email",
                "jsonType.label": "String"
            }
        },
        {
            "id": "193edec2-673e-4594-91ee-7bd359a6eb68",
            "name": "full name",
            "protocol": "openid-connect",
            "protocolMapper": "oidc-full-name-mapper",
            "consentRequired": true,
            "consentText": "${fullName}",
            "config": {
                "id.token.claim": "true",
                "access.token.claim": "true"
            }
        },
        {
            "id": "0ff15955-2a0c-4db9-bc55-599027c37545",
            "name": "family name",
            "protocol": "openid-connect",
            "protocolMapper": "oidc-usermodel-property-mapper",
            "consentRequired": true,
            "consentText": "${familyName}",
            "config": {
                "user.attribute": "lastName",
                "id.token.claim": "true",
                "access.token.claim": "true",
                "claim.name": "family_name",
                "jsonType.label": "String"
            }
        },
        {
            "id": "dd036988-d950-45a6-be55-170ed1a27129",
            "name": "Client Host",
            "protocol": "openid-connect",
            "protocolMapper": "oidc-usersessionmodel-note-mapper",
            "consentRequired": false,
            "consentText": "",
            "config": {
                "user.session.note": "clientHost",
                "id.token.claim": "true",
                "access.token.claim": "true",
                "claim.name": "clientHost",
                "jsonType.label": "String"
            }
        },
        {
            "id": "f7af33a2-70bc-4508-b64b-a0b71d17de1c",
            "name": "Client IP Address",
            "protocol": "openid-connect",
            "protocolMapper": "oidc-usersessionmodel-note-mapper",
            "consentRequired": false,
            "consentText": "",
            "config": {
                "user.session.note": "clientAddress",
                "id.token.claim": "true",
                "access.token.claim": "true",
                "claim.name": "clientAddress",
                "jsonType.label": "String"
            }
        },
        {
            "id": "f271e1ee-8104-49de-9f02-de054864a49e",
            "name": "username",
            "protocol": "openid-connect",
            "protocolMapper": "oidc-usermodel-property-mapper",
            "consentRequired": true,
            "consentText": "${username}",
            "config": {
                "user.attribute": "username",
                "id.token.claim": "true",
                "access.token.claim": "true",
                "claim.name": "preferred_username",
                "jsonType.label": "String"
            }
        },
        {
            "id": "7219165b-a410-4ab1-9747-c4a326af3896",
            "name": "Client ID",
            "protocol": "openid-connect",
            "protocolMapper": "oidc-usersessionmodel-note-mapper",
            "consentRequired": false,
            "consentText": "",
            "config": {
                "user.session.note": "clientId",
                "id.token.claim": "true",
                "access.token.claim": "true",
                "claim.name": "clientId",
                "jsonType.label": "String"
            }
        }
    ],
    "useTemplateConfig": false,
    "useTemplateScope": false,
    "useTemplateMappers": false
}